generativenetworkmodels-1.0.dist-info/licenses/LICENSE.txt
gnm/__init__.py
gnm/model.py
gnm/defaults/__init__.py
gnm/defaults/generate_heterochronous_matrix.py
gnm/defaults/get_defaults.py
gnm/evaluation/__init__.py
gnm/evaluation/binary_corr_criteria.py
gnm/evaluation/binary_ks_criteria.py
gnm/evaluation/composite_criteria.py
gnm/evaluation/evaluation_base.py
gnm/evaluation/population_evaluation.py
gnm/evaluation/weighted_corr_criteria.py
gnm/evaluation/weighted_ks_criteria.py
gnm/fitting/__init__.py
gnm/fitting/analysis.py
gnm/fitting/experiment_dataclasses.py
gnm/fitting/experiment_saving.py
gnm/fitting/sweep.py
gnm/generative_rules/__init__.py
gnm/generative_rules/generative_rules.py
gnm/utils/__init__.py
gnm/utils/checks.py
gnm/utils/control.py
gnm/utils/convert_datatypes.py
gnm/utils/graph_properties.py
gnm/utils/statistics.py
gnm/weight_criteria/__init__.py
gnm/weight_criteria/optimisation_criteria.py
generativenetworkmodels-1.0.dist-info/METADATA
generativenetworkmodels-1.0.dist-info/WHEEL
generativenetworkmodels-1.0.dist-info/top_level.txt
generativenetworkmodels-1.0.dist-info/RECORD
