Metadata-Version: 2.4
Name: GenerativeNetworkModels
Version: 1.0
Summary: This package provides computationally efficient tools for implementing Weighted
Home-page: https://github.com/EdwardJamesYoung/GenerativeNetworkModels
Author: Edward Young, Francesco Poli, William Mills
Author-email: Edward Young <ey245@cam.ac.uk>, William Mills <william.mills@mrc-cbu.cam.ac.uk>, Francesco Poli <francesco.poli@mrc-cbu.cam.ac.uk>
License: MIT
Project-URL: Homepage, https://github.com/EdwardJamesYoung/GenerativeNetworkModels
Project-URL: Documentation, https://generative-network-models-toolbox.readthedocs.io/en/latest/
Project-URL: Repository, https://github.com/EdwardJamesYoung/GenerativeNetworkModels.git
Project-URL: Bug Tracker, https://github.com/EdwardJamesYoung/GenerativeNetworkModels/issues
Keywords: network-science,neuroscience,generative-models,weighted-networks,brain-connectivity,network-analysis,graph-theory,connectomics
Classifier: Development Status :: 1 - Planning
Classifier: Intended Audience :: Science/Research
Classifier: Intended Audience :: Developers
Classifier: Topic :: Scientific/Engineering :: Artificial Intelligence
Classifier: Topic :: Scientific/Engineering :: Mathematics
Classifier: Topic :: Scientific/Engineering :: Medical Science Apps.
Classifier: Programming Language :: Python :: 3.9
Classifier: Programming Language :: Python :: 3.10
Classifier: Programming Language :: Python :: 3.11
Classifier: Programming Language :: Python :: 3.12
Classifier: Framework :: Jupyter
Classifier: License :: OSI Approved :: MIT License
Requires-Python: >=3.9
License-File: LICENSE.txt
Requires-Dist: jaxtyping==0.2.36
Requires-Dist: setuptools==75.1.0
Requires-Dist: six==1.16.0
Requires-Dist: sympy==1.13.3
Requires-Dist: tqdm==4.66.5
Requires-Dist: typeguard==2.13.3
Requires-Dist: typing-extensions==4.12.2
Requires-Dist: urllib3==2.3.0
Requires-Dist: wheel==0.44.0
Requires-Dist: zipp==3.21.0
Requires-Dist: wandb==0.15.12
Requires-Dist: numpy==1.26.4
Dynamic: author
Dynamic: home-page
Dynamic: license-file
Dynamic: requires-python
